zerophone_api_daemon/__init__.py
zerophone_api_daemon/rpc_api.py
zerophone_api_daemon/sources.py
zerophone_api_daemon/zerophone_api_daemon.py
zerophone_api_daemon-0.1.0.dist-info/DESCRIPTION.rst
zerophone_api_daemon-0.1.0.dist-info/METADATA
zerophone_api_daemon-0.1.0.dist-info/RECORD
zerophone_api_daemon-0.1.0.dist-info/WHEEL
zerophone_api_daemon-0.1.0.dist-info/metadata.json
zerophone_api_daemon-0.1.0.dist-info/top_level.txt
